main.py
random_quote_retriever-0.1.2.dist-info/licenses/LICENSE
random_quote_retriever-0.1.2.dist-info/METADATA
random_quote_retriever-0.1.2.dist-info/WHEEL
random_quote_retriever-0.1.2.dist-info/entry_points.txt
random_quote_retriever-0.1.2.dist-info/top_level.txt
random_quote_retriever-0.1.2.dist-info/RECORD
