Metadata-Version: 2.4
Name: random-quote-retriever
Version: 0.1.2
Summary: A simple CLI tool to fetch random quotes from ZenQuotes API
Author-email: Muhammad Hasan <mhasanali210@google.com>
License: MIT
Requires-Python: >=3.9
License-File: LICENSE
Requires-Dist: requests>=2.32.3
Dynamic: license-file
